semantic_dictionary/__init__.py
semantic_dictionary/adapters.py
semantic_dictionary/semantic_dictionary.py
semantic_dictionary-0.1.0.dist-info/licenses/LICENSE
semantic_dictionary-0.1.0.dist-info/METADATA
semantic_dictionary-0.1.0.dist-info/WHEEL
semantic_dictionary-0.1.0.dist-info/top_level.txt
semantic_dictionary-0.1.0.dist-info/RECORD
