Metadata-Version: 2.4
Name: semantic-dictionary
Version: 0.1.0
Summary: A dictionary-like class that uses semantic similarity for key matching
Author-email: "Stefan (eu90h)" <stefan@eu90h.com>
License-Expression: MIT
Project-URL: Homepage, https://github.com/eu90h/semantic-dictionary
Project-URL: Bug Tracker, https://github.com/eu90h/semantic-dictionary/issues
Project-URL: Documentation, https://github.com/eu90h/semantic-dictionary#readme
Keywords: semantic,dictionary,similarity,embeddings,nlp
Classifier: Development Status :: 4 - Beta
Classifier: Programming Language :: Python :: 3
Classifier: Programming Language :: Python :: 3.7
Classifier: Programming Language :: Python :: 3.8
Classifier: Programming Language :: Python :: 3.9
Classifier: Programming Language :: Python :: 3.10
Classifier: Programming Language :: Python :: 3.11
Classifier: Programming Language :: Python :: 3.12
Classifier: Programming Language :: Python :: 3.13
Classifier: Operating System :: OS Independent
Classifier: Topic :: Software Development :: Libraries :: Python Modules
Classifier: Intended Audience :: Developers
Classifier: Intended Audience :: Science/Research
Requires-Python: >=3.7
License-File: LICENSE
Requires-Dist: numpy>=1.19.0
Provides-Extra: sentence-transformers
Requires-Dist: sentence-transformers>=2.0.0; extra == "sentence-transformers"
Provides-Extra: huggingface
Requires-Dist: transformers>=4.0.0; extra == "huggingface"
Requires-Dist: torch>=1.7.0; extra == "huggingface"
Provides-Extra: openai
Requires-Dist: openai>=1.0.0; extra == "openai"
Provides-Extra: all
Requires-Dist: sentence-transformers>=2.0.0; extra == "all"
Requires-Dist: transformers>=4.0.0; extra == "all"
Requires-Dist: torch>=1.7.0; extra == "all"
Requires-Dist: openai>=1.0.0; extra == "all"
Provides-Extra: dev
Requires-Dist: black; extra == "dev"
Requires-Dist: isort; extra == "dev"
Requires-Dist: pytest; extra == "dev"
Dynamic: license-file
